enummi/README.MD
enummi/__init__.py
enummi/requirements.txt
enummi/thirdparty.json
enummi-0.10.dist-info/LICENSE.rst
enummi-0.10.dist-info/METADATA
enummi-0.10.dist-info/WHEEL
enummi-0.10.dist-info/top_level.txt
enummi-0.10.dist-info/RECORD
