Metadata-Version: 2.1
Name: enummi
Version: 0.10
Summary: I love enumerate(), but I hate using it with zip() - this function takes care of it
Home-page: https://github.com/hansalemaos/enummi
Author: Johannes Fischer
Author-email: aulasparticularesdealemaosp@gmail.com
License: MIT
Keywords: enumerate,zip
Classifier: Development Status :: 4 - Beta
Classifier: Programming Language :: Python :: 3 :: Only
Classifier: Programming Language :: Python :: 3.10
Classifier: Topic :: Software Development :: Libraries :: Python Modules
Classifier: Topic :: Utilities
License-File: LICENSE.rst
